pulsar_viewer/__init__.py
pulsar_viewer/__main__.py
pulsar_viewer/pulsar/__init__.py
pulsar_viewer/pulsar/_msg.py
pulsar_viewer/pulsar/_poller.py
pulsar_viewer/toga/__init__.py
pulsar_viewer/toga/main.py
pulsar_viewer/toga/app/__init__.py
pulsar_viewer/toga/app/_ctrl.py
pulsar_viewer/toga/main_window/__init__.py
pulsar_viewer/toga/main_window/_ctrl.py
pulsar_viewer/toga/main_window/_structs.py
pulsar_viewer/toga/main_window/_vm.py
pulsar_viewer-0.1.0.dist-info/METADATA
pulsar_viewer-0.1.0.dist-info/WHEEL
pulsar_viewer-0.1.0.dist-info/entry_points.txt
pulsar_viewer-0.1.0.dist-info/licenses/LICENSE.txt
pulsar_viewer-0.1.0.dist-info/RECORD
