Metadata-Version: 2.3
Name: pulsar-viewer
Version: 0.1.0
Summary: Add your description here
Author-email: alexjuda <alexanderjuda@gmail.com>
License: Apache-2.0
License-File: LICENSE.txt
Requires-Python: >=3.10
Requires-Dist: click>=8.1.7
Requires-Dist: pulsar-client>=3.5.0
Requires-Dist: toga>=0.4.5
